crawl_tool.py
crawl_tool-0.0.2.dist-info/LICENSE
crawl_tool-0.0.2.dist-info/METADATA
crawl_tool-0.0.2.dist-info/WHEEL
crawl_tool-0.0.2.dist-info/top_level.txt
crawl_tool-0.0.2.dist-info/RECORD
