Metadata-Version: 2.1
Name: crawl-tool
Version: 0.0.2
Summary: Tool class for web crawling
Home-page: https://github.com/MemoryAndDream
Author: zhihao.meng
Author-email: meng631011@gmail.com
License: UNKNOWN
Platform: UNKNOWN
Classifier: Programming Language :: Python :: 3
Classifier: License :: OSI Approved :: MIT License
Classifier: Operating System :: OS Independent
Requires-Python: >=3.6
